detic/__init__.py
detic/config.py
detic/custom_solver.py
detic/predictor.py
detic/data/custom_build_augmentation.py
detic/data/custom_dataset_dataloader.py
detic/data/custom_dataset_mapper.py
detic/data/tar_dataset.py
detic/data/datasets/cc.py
detic/data/datasets/coco_zeroshot.py
detic/data/datasets/imagenet.py
detic/data/datasets/lvis_22k_categories.py
detic/data/datasets/lvis_v1.py
detic/data/datasets/objects365.py
detic/data/datasets/oid.py
detic/data/datasets/register_oid.py
detic/data/transforms/custom_augmentation_impl.py
detic/data/transforms/custom_transform.py
detic/evaluation/custom_coco_eval.py
detic/evaluation/oideval.py
detic/modeling/debug.py
detic/modeling/utils.py
detic/modeling/backbone/swintransformer.py
detic/modeling/backbone/timm.py
detic/modeling/meta_arch/custom_rcnn.py
detic/modeling/meta_arch/d2_deformable_detr.py
detic/modeling/roi_heads/detic_fast_rcnn.py
detic/modeling/roi_heads/detic_roi_heads.py
detic/modeling/roi_heads/res5_roi_heads.py
detic/modeling/roi_heads/zero_shot_classifier.py
detic/modeling/text/text_encoder.py
detic_fast-1.0.post20230203.dist-info/LICENSE
detic_fast-1.0.post20230203.dist-info/METADATA
detic_fast-1.0.post20230203.dist-info/WHEEL
detic_fast-1.0.post20230203.dist-info/top_level.txt
detic_fast-1.0.post20230203.dist-info/RECORD
